codeorite/__init__.py
codeorite/__main__.py
codeorite/cli.py
codeorite/config.py
codeorite/logging.py
codeorite/main.py
codeorite-0.2.4.dist-info/LICENSE
codeorite-0.2.4.dist-info/METADATA
codeorite-0.2.4.dist-info/WHEEL
codeorite-0.2.4.dist-info/entry_points.txt
codeorite-0.2.4.dist-info/top_level.txt
codeorite-0.2.4.dist-info/RECORD
