Metadata-Version: 2.1
Name: codeorite
Version: 0.2.4
Summary: A tool to package a repository into a single text file while respecting .gitignore.
Author-email: Brad Edwards <brad@keplerops.com>
License: MIT
Project-URL: homepage, https://github.com/KeplerOps/codeorite
Project-URL: repository, https://github.com/KeplerOps/codeorite
Project-URL: documentation, https://github.com/KeplerOps/codeorite/blob/main/README.md
Keywords: pack,repository,gitignore,language includes,tree
Classifier: Programming Language :: Python :: 3
Classifier: License :: OSI Approved :: MIT License
Requires-Python: >=3.7
License-File: LICENSE
Requires-Dist: pathspec>=0.9.0
Requires-Dist: PyYAML>=6.0
Provides-Extra: dev
Requires-Dist: pytest; extra == "dev"
Requires-Dist: pathspec>=0.9.0; extra == "dev"
Requires-Dist: pyyaml>=6.0; extra == "dev"
